textual_wizard/__init__.py
textual_wizard/__main__.py
textual_wizard/exceptions.py
textual_wizard/inputs.py
textual_wizard/py.typed
textual_wizard/wizard.py
textual_wizard/wizard.tcss
textual_wizard-0.4.3.dist-info/entry_points.txt
textual_wizard-0.4.3.dist-info/LICENSE
textual_wizard-0.4.3.dist-info/WHEEL
textual_wizard-0.4.3.dist-info/METADATA
textual_wizard-0.4.3.dist-info/RECORD
