Metadata-Version: 2.1
Name: textual-wizard
Version: 0.4.3
Summary: Easily ask for input with a beautiful user interface, within the terminal.
Author-email: Leopold Koprivnik <skwal@etik.com>
Requires-Python: >=3.9
Classifier: License :: OSI Approved :: GNU General Public License v3 or later (GPLv3+)
Requires-Dist: textual>=0.66.0
Requires-Dist: rich>=13.7.1
Requires-Dist: click-extra>=4.8.3
Requires-Dist: inquirer>=3.3.0
Project-URL: Home, https://github.com/SkwalExe/textual-wizard
